LICENSE
README.rst
setup.py
grape/__init__.py
grape/__version__.py
grape.egg-info/PKG-INFO
grape.egg-info/SOURCES.txt
grape.egg-info/dependency_links.txt
grape.egg-info/requires.txt
grape.egg-info/top_level.txt
tests/test_imports.py