Metadata-Version: 1.1
Name: grape
Version: 0.2.2
Summary: 🍇 GRAPE is a Rust/Python Graph Representation Learning library for Predictions and Evaluations.
Home-page: https://github.com/AnacletoLAB/grape
Author: Luca Cappelletti, Tommaso Fontana, Vida Ravanmehr, Peter Robinson
Author-email: luca.cappelletti1@unimi.it, tommaso.fontana@mail.polimi.it, vida.ravanmehr@jax.org, peter.robinson@jax.org
License: MIT
Platform: UNKNOWN
Classifier: Development Status :: 4 - Beta
Classifier: License :: OSI Approved :: MIT License
Classifier: Programming Language :: Python :: 3
